FresnoPython/__init__.py
FresnoPython/compat.py
FresnoPython/utils.py
FresnoPython-1.0.0.data/scripts/fresno.py
FresnoPython-1.0.0.dist-info/DESCRIPTION.rst
FresnoPython-1.0.0.dist-info/METADATA
FresnoPython-1.0.0.dist-info/RECORD
FresnoPython-1.0.0.dist-info/WHEEL
FresnoPython-1.0.0.dist-info/metadata.json
FresnoPython-1.0.0.dist-info/top_level.txt
