Metadata-Version: 2.0
Name: FresnoPython
Version: 1.0.0
Summary: Information for the Fresno Python User Group
Home-page: https://github.com/dmpayton/FresnoPython
Author: Derek Payton
Author-email: derek.payton@gmail.com
License: MIT
Keywords: fresno user group
Platform: UNKNOWN
Classifier: Development Status :: 3 - Alpha
Classifier: Intended Audience :: Developers
Classifier: License :: OSI Approved :: MIT License
Classifier: Natural Language :: English
Classifier: Programming Language :: Python
Classifier: Programming Language :: Python :: 2.7
Classifier: Programming Language :: Python :: 3.5
Classifier: Topic :: Software Development :: Libraries :: Python Modules
Requires-Dist: python-dateutil (==2.5.3)
